Metadata-Version: 1.0
Name: ai-distributions
Version: 0.1
Summary: Gaussian distributions
Home-page: UNKNOWN
Author: Asif Iqbal
Author-email: iqmazif@gmail.com
License: UNKNOWN
Platform: UNKNOWN
